[
    {
        "title": "Damage Prediction by Wildfires (March 2025)",
        "image": "https://vis-society.github.io/labs/2/images/empty.svg",
        "description": "Developed ML model to predict wildfire damage using CAL FIRE data, Applied data cleaning, EDA, feature engineering, and model optimization\n              Evaluated Logistic Regression, Random Forest, XGBoost, LightGBM, Deployed an interactive demo for real-time risk assessment: \n              Demo | Paper\n            "
    },
    {
        "title": "Healthy Recipes Analysis Website (Nov. 2024 - Dec. 2024)",
        "image": "https://vis-society.github.io/labs/2/images/empty.svg",
        "description": "Analyzed food.com recipes using hypothesis testing and EDA, Built Random Forest model with 95% test accuracy, Created Plotly visualizations embedded on GitHub Pages:\n              Website\n            "
    },
    {
        "title": "MBTI Guessr",
        "image": "https://vis-society.github.io/labs/2/images/empty.svg",
        "description": "-In Progress-"
    },
    {
        "title": "In Progress",
        "image": "https://vis-society.github.io/labs/2/images/empty.svg",
        "description": "-In Progress-"
    },
    {
        "title": "In Progress",
        "image": "https://vis-society.github.io/labs/2/images/empty.svg",
        "description": "-In Progress-"
    },
    {
        "title": "In Progress",
        "image": "https://vis-society.github.io/labs/2/images/empty.svg",
        "description": "-In Progress-"
    },
    {
        "title": "In Progress",
        "image": "https://vis-society.github.io/labs/2/images/empty.svg",
        "description": "-In Progress-"
    },
    {
        "title": "In Progress",
        "image": "https://vis-society.github.io/labs/2/images/empty.svg",
        "description": "-In Progress-"
    },
    {
        "title": "In Progress",
        "image": "https://vis-society.github.io/labs/2/images/empty.svg",
        "description": "-In Progress-"
    },
    {
        "title": "MBTI Guessr",
        "image": "https://vis-society.github.io/labs/2/images/empty.svg",
        "description": "-In Progress-"
    },
    {
        "title": "MBTI Guessr",
        "image": "https://vis-society.github.io/labs/2/images/empty.svg",
        "description": "-In Progress-"
    },
    {
        "title": "MBTI Guessr",
        "image": "https://vis-society.github.io/labs/2/images/empty.svg",
        "description": "-In Progress-"
    }
]